ragentools/__init__.py
ragentools/api_calls/__init__.py
ragentools/api_calls/base_api.py
ragentools/api_calls/google_gemini.py
ragentools/api_calls/langchain_runnable.py
ragentools/api_calls/openai_gpt.py
ragentools/api_calls/prices.csv
ragentools/common/async_funcs.py
ragentools/common/dynamic_retry.py
ragentools/common/formatting.py
ragentools/evaluators/__init__.py
ragentools/evaluators/base.py
ragentools/evaluators/evaluators.py
ragentools/genqa/genqa.py
ragentools/parsers/__init__.py
ragentools/parsers/chunkers.py
ragentools/parsers/converters.py
ragentools/parsers/parsers.py
ragentools/parsers/readers.py
ragentools/parsers/savers.py
ragentools/prompts/__init__.py
ragentools/prompts/agentic_rag/is_sufficient.yaml
ragentools/prompts/agentic_rag/need_retrieval.yaml
ragentools/prompts/agentic_rag/query_decomposer.yaml
ragentools/prompts/agentic_rag/query_fixer.yaml
ragentools/prompts/basic.yaml
ragentools/prompts/genqa/basic.yaml
ragentools/prompts/ragas/advisor.yaml
ragentools/prompts/ragas/ragas/answer_correctness.yaml
ragentools/prompts/ragas/ragas/answer_relevancy.yaml
ragentools/prompts/ragas/ragas/context_precision.yaml
ragentools/prompts/ragas/ragas/context_recall.yaml
ragentools/prompts/ragas/ragas/faithfulness.yaml
ragentools/prompts/reranker.yaml
ragentools/prompts/text2chart/eval.yaml
ragentools/prompts/text2chart/fix.yaml
ragentools/prompts/text2chart/gen.yaml
ragentools/prompts/text2chart/refine.yaml
ragentools/rags/__init__.py
ragentools/rags/agentic_rag.py
ragentools/rags/rag_engines.py
ragentools/rags/rags.py
ragentools/rags/rerankers.py
ragentools/rags/utils/embedding.py
ragentools/rags/utils/summarizer.py
ragentools/rags/utils/vectorstore_adapters.py
ragentools-1.0.0.dist-info/licenses/LICENSE
ragentools-1.0.0.dist-info/METADATA
ragentools-1.0.0.dist-info/WHEEL
ragentools-1.0.0.dist-info/RECORD
