Metadata-Version: 2.4
Name: ragentools
Version: 1.0.0
Summary: 
License-File: LICENSE
Author: JamesChao
Requires-Python: >=3.10,<3.13
Classifier: Programming Language :: Python :: 3
Classifier: Programming Language :: Python :: 3.10
Classifier: Programming Language :: Python :: 3.11
Classifier: Programming Language :: Python :: 3.12
Requires-Dist: faiss-cpu (>=1.12.0,<2.0.0)
Requires-Dist: google-genai (>=1.46.0,<2.0.0)
Requires-Dist: graphrag (>=2.7.0,<3.0.0)
Requires-Dist: langchain-community (>=0.4.1,<0.5.0)
Requires-Dist: langchain-google-genai (>=3.0.0,<4.0.0)
Requires-Dist: langgraph (>=1.0.2,<2.0.0)
Requires-Dist: openai (>=2.6.1,<3.0.0)
Requires-Dist: pandas (>=2.3.3,<3.0.0)
Requires-Dist: pymupdf (>=1.26.5,<2.0.0)
Requires-Dist: tenacity (>=9.1.2,<10.0.0)
